travistomek/__init__.py
travistomek/generalutils.py
travistomek/guard.py
travistomek-0.0.5.dist-info/AUTHORS.rst
travistomek-0.0.5.dist-info/METADATA
travistomek-0.0.5.dist-info/WHEEL
travistomek-0.0.5.dist-info/top_level.txt
travistomek-0.0.5.dist-info/RECORD
