Metadata-Version: 2.1
Name: travistomek
Version: 0.0.5
Summary: This package contains some common general utilisations modules
Home-page: https://github.com/Tomekske/travistomek
Author: Tomek Joostens
Author-email: joostenstomek@gmail.com
License: MIT license
Keywords: travistomek
Platform: UNKNOWN
Classifier: Development Status :: 2 - Pre-Alpha
Classifier: Intended Audience :: Developers
Classifier: License :: OSI Approved :: MIT License
Classifier: Natural Language :: English
Classifier: Programming Language :: Python :: 3
Classifier: Programming Language :: Python :: 3.7
